{
	"name": "Dataset_FileSink_CSV",
	"properties": {
		"linkedServiceName": {
			"referenceName": "Data_Lake",
			"type": "LinkedServiceReference"
		},
		"annotations": [],
		"type": "DelimitedText",
		"typeProperties": {
			"location": {
				"type": "AzureBlobFSLocation",
				"fileName": "credit6.csv",
				"folderPath": "CSV",
				"fileSystem": "team-nexus"
			},
			"columnDelimiter": ",",
			"escapeChar": "\\",
			"firstRowAsHeader": true,
			"quoteChar": "\""
		},
		"schema": []
	},
	"type": "Microsoft.Synapse/workspaces/datasets"
}